<?xml version="1.0" ?>
<!--####################
This comment tag is auto-generated by DBTool. Do not manually edit!
FileType:instance
AccessType:ReadWrite
FileRevision:1.0
####################--><Device>
  <DSL>
    <LineNumberOfEntries node="parameter">2</LineNumberOfEntries>
    <ChannelNumberOfEntries node="parameter">2</ChannelNumberOfEntries>
    <BondingGroupNumberOfEntries node="parameter">0</BondingGroupNumberOfEntries>
	<X_LANTIQ_COM_Config node="object">
		<Enable node="parameter">true</Enable>
		<BitswapUs_V node="parameter">1</BitswapUs_V>
		<BitswapUs_A node="parameter">1</BitswapUs_A>
		<BitswapDs_V node="parameter">1</BitswapDs_V>
		<BitswapDs_A node="parameter">1</BitswapDs_A>
		<ReTxUs node="parameter">1</ReTxUs>
		<ReTxDs_V node="parameter">1</ReTxDs_V>
		<ReTxDs_A node="parameter">0</ReTxDs_A>
		<SraUs_V node="parameter">1</SraUs_V>
		<SraUs_A node="parameter">0</SraUs_A>
		<SraDs_V node="parameter">1</SraDs_V>
		<SraDs_A node="parameter">0</SraDs_A>
		<VirtualNoiseUs node="parameter">1</VirtualNoiseUs>
		<VirtualNoiseDs node="parameter">1</VirtualNoiseDs>
		<Vectoring node="parameter">Auto</Vectoring>
		<XTSE node="parameter">0x5 0x0 0x4 0x0 0xC 0x1 0x0 0x7</XTSE>
		<XTSE_Modes node="parameter">1,4,5,6,8,10</XTSE_Modes>
		<LinkEncapsulationConfig node="parameter">G.992.3_Annex_K_ATM,G.993.2_Annex_K_PTM</LinkEncapsulationConfig>
		<DSLNextMode node="parameter">VDSL</DSLNextMode>
		<NextTCMode node="parameter">ptm</NextTCMode>
		<DSLActSeq node="parameter">Auto</DSLActSeq>
		<DSLActMode node="parameter">GHS</DSLActMode>
		<DSLRemember node="parameter">1</DSLRemember>
	</X_LANTIQ_COM_Config>
    <Line Instance="1" node="object">
      <Enable node="parameter">true</Enable>
      <EnableDataGathering node="parameter">0</EnableDataGathering>
      <Status node="parameter">Down</Status>
      <Alias node="parameter"/>
      <Name node="parameter"></Name>
      <LastChange node="parameter">0</LastChange>
      <LowerLayers node="parameter"/>
      <Upstream node="parameter">0</Upstream>
      <FirmwareVersion node="parameter"/>
      <LinkStatus node="parameter">Down</LinkStatus>
      <StandardsSupported node="parameter"/>
      <XTSE node="parameter">0000000000000000</XTSE>
      <StandardUsed node="parameter"/>
      <XTSUsed node="parameter">0000000000000000</XTSUsed>
      <LineEncoding node="parameter">DMT</LineEncoding>
      <AllowedProfiles node="parameter"/>
      <CurrentProfile node="parameter"/>
      <PowerManagementState node="parameter">L0</PowerManagementState>
      <SuccessFailureCause node="parameter">0</SuccessFailureCause>
      <UPBOKLER node="parameter">0</UPBOKLER>
      <UPBOKLEPb node="parameter">2047</UPBOKLEPb>
      <UPBOKLERPb node="parameter">2047</UPBOKLERPb>
      <RXTHRSHds node="parameter">0</RXTHRSHds>
      <ACTRAMODEds node="parameter">1</ACTRAMODEds>
      <ACTRAMODEus node="parameter">1</ACTRAMODEus>
      <ACTINPROCds node="parameter">0</ACTINPROCds>
      <ACTINPROCus node="parameter">0</ACTINPROCus>
      <SNRMROCds node="parameter">0</SNRMROCds>
      <SNRMROCus node="parameter">0</SNRMROCus>
      <LastStateTransmittedDownstream node="parameter">0</LastStateTransmittedDownstream>
      <LastStateTransmittedUpstream node="parameter">0</LastStateTransmittedUpstream>
      <UPBOKLE node="parameter">0</UPBOKLE>
      <MREFPSDds node="parameter">0</MREFPSDds>
      <MREFPSDus node="parameter">0</MREFPSDus>
      <LIMITMASK node="parameter">0</LIMITMASK>
      <US0MASK node="parameter">0</US0MASK>
      <TRELLISds node="parameter">0</TRELLISds>
      <TRELLISus node="parameter">0</TRELLISus>
      <ACTSNRMODEds node="parameter">0</ACTSNRMODEds>
      <ACTSNRMODEus node="parameter">0</ACTSNRMODEus>
      <VirtualNoisePSDds node="parameter">0</VirtualNoisePSDds>
      <VirtualNoisePSDus node="parameter">0</VirtualNoisePSDus>
      <ACTUALCE node="parameter">0</ACTUALCE>
      <LineNumber node="parameter">0</LineNumber>
      <UpstreamMaxBitRate node="parameter">0</UpstreamMaxBitRate>
      <DownstreamMaxBitRate node="parameter">0</DownstreamMaxBitRate>
      <UpstreamNoiseMargin node="parameter">0</UpstreamNoiseMargin>
      <DownstreamNoiseMargin node="parameter">0</DownstreamNoiseMargin>
      <SNRMpbus node="parameter"/>
      <SNRMpbds node="parameter"/>
      <INMIATOds node="parameter">3</INMIATOds>
      <INMIATSds node="parameter">0</INMIATSds>
      <INMCCds node="parameter">0</INMCCds>
      <INMINPEQMODEds node="parameter">0</INMINPEQMODEds>
      <UpstreamAttenuation node="parameter">0</UpstreamAttenuation>
      <DownstreamAttenuation node="parameter">0</DownstreamAttenuation>
      <UpstreamPower node="parameter">0</UpstreamPower>
      <DownstreamPower node="parameter">0</DownstreamPower>
      <XTURVendor node="parameter">00000000</XTURVendor>
      <XTURCountry node="parameter">0000</XTURCountry>
      <XTURANSIStd node="parameter">0</XTURANSIStd>
      <XTURANSIRev node="parameter">0</XTURANSIRev>
      <XTUCVendor node="parameter">00000000</XTUCVendor>
      <XTUCCountry node="parameter">0000</XTUCCountry>
      <XTUCANSIStd node="parameter">0</XTUCANSIStd>
      <XTUCANSIRev node="parameter">0</XTUCANSIRev>
      <DataGathering node="object">
        <LoggingDepthR node="parameter">0</LoggingDepthR>
        <ActLoggingDepthReportingR node="parameter">0</ActLoggingDepthReportingR>
        <EventTraceBufferR node="parameter"/>
      </DataGathering>
      <Stats node="object">
        <BytesSent node="parameter">0</BytesSent>
        <BytesReceived node="parameter">0</BytesReceived>
        <PacketsSent node="parameter">0</PacketsSent>
        <PacketsReceived node="parameter">0</PacketsReceived>
        <ErrorsSent node="parameter">0</ErrorsSent>
        <ErrorsReceived node="parameter">0</ErrorsReceived>
        <DiscardPacketsSent node="parameter">0</DiscardPacketsSent>
        <DiscardPacketsReceived node="parameter">0</DiscardPacketsReceived>
        <TotalStart node="parameter">0</TotalStart>
        <ShowtimeStart node="parameter">0</ShowtimeStart>
        <LastShowtimeStart node="parameter">0</LastShowtimeStart>
        <CurrentDayStart node="parameter">0</CurrentDayStart>
        <QuarterHourStart node="parameter">0</QuarterHourStart>
        <Total node="object">
          <ErroredSecs node="parameter">0</ErroredSecs>
          <SeverelyErroredSecs node="parameter">0</SeverelyErroredSecs>
        </Total>
        <Showtime node="object">
          <ErroredSecs node="parameter">0</ErroredSecs>
          <SeverelyErroredSecs node="parameter">0</SeverelyErroredSecs>
        </Showtime>
        <LastShowtime node="object">
          <ErroredSecs node="parameter">0</ErroredSecs>
          <SeverelyErroredSecs node="parameter">0</SeverelyErroredSecs>
        </LastShowtime>
        <CurrentDay node="object">
          <ErroredSecs node="parameter">0</ErroredSecs>
          <SeverelyErroredSecs node="parameter">0</SeverelyErroredSecs>
        </CurrentDay>
        <QuarterHour node="object">
          <ErroredSecs node="parameter">0</ErroredSecs>
          <SeverelyErroredSecs node="parameter">0</SeverelyErroredSecs>
        </QuarterHour>
      </Stats>
      <TestParams node="object">
        <HLOGGds node="parameter">0</HLOGGds>
        <HLOGGus node="parameter">0</HLOGGus>
        <HLOGpsds node="parameter"/>
        <HLOGpsus node="parameter"/>
        <HLOGMTds node="parameter">0</HLOGMTds>
        <HLOGMTus node="parameter">0</HLOGMTus>
        <QLNGds node="parameter">0</QLNGds>
        <QLNGus node="parameter">0</QLNGus>
        <QLNpsds node="parameter">0</QLNpsds>
        <QLNpsus node="parameter">0</QLNpsus>
        <QLNMTds node="parameter">0</QLNMTds>
        <QLNMTus node="parameter">0</QLNMTus>
        <SNRGds node="parameter">0</SNRGds>
        <SNRGus node="parameter">0</SNRGus>
        <SNRpsds node="parameter">0</SNRpsds>
        <SNRpsus node="parameter">0</SNRpsus>
        <SNRMTds node="parameter">0</SNRMTds>
        <SNRMTus node="parameter">0</SNRMTus>
        <LATNds node="parameter"/>
        <LATNus node="parameter"/>
        <SATNds node="parameter"/>
        <SATNus node="parameter"/>
      </TestParams>
    </Line>
    <Channel Instance="1" node="object">
      <Enable node="parameter">1</Enable>
      <Status node="parameter">Down</Status>
      <Alias node="parameter"/>
      <Name node="parameter"/>
      <LastChange node="parameter">0</LastChange>
      <LowerLayers node="parameter"/>
      <LinkEncapsulationSupported node="parameter">G.994.1(Auto)</LinkEncapsulationSupported>
      <LinkEncapsulationUsed node="parameter">G.993.2_Annex_K_PTM</LinkEncapsulationUsed>
      <LPATH node="parameter">0</LPATH>
      <INTLVDEPTH node="parameter">0</INTLVDEPTH>
      <INTLVBLOCK node="parameter">0</INTLVBLOCK>
      <ActualInterleavingDelay node="parameter">0</ActualInterleavingDelay>
      <ACTINP node="parameter">0</ACTINP>
      <INPREPORT node="parameter">0</INPREPORT>
      <NFEC node="parameter">0</NFEC>
      <RFEC node="parameter">0</RFEC>
      <LSYMB node="parameter">0</LSYMB>
      <UpstreamCurrRate node="parameter">0</UpstreamCurrRate>
      <DownstreamCurrRate node="parameter">0</DownstreamCurrRate>
      <ACTNDR node="parameter">0</ACTNDR>
      <X_LANTIQ_COM_ACTNDRds node="parameter">0</X_LANTIQ_COM_ACTNDRds>
      <X_LANTIQ_COM_ACTNDRus node="parameter">0</X_LANTIQ_COM_ACTNDRus>
      <ACTINPREIN node="parameter">0</ACTINPREIN>
      <X_LANTIQ_COM_ACTINPREINds node="parameter">0</X_LANTIQ_COM_ACTINPREINds>
      <X_LANTIQ_COM_ACTINPREINus node="parameter">0</X_LANTIQ_COM_ACTINPREINus>
      <Stats node="object">
        <BytesSent node="parameter">0</BytesSent>
        <BytesReceived node="parameter">0</BytesReceived>
        <PacketsSent node="parameter">0</PacketsSent>
        <PacketsReceived node="parameter">0</PacketsReceived>
        <ErrorsSent node="parameter">0</ErrorsSent>
        <ErrorsReceived node="parameter">0</ErrorsReceived>
        <DiscardPacketsSent node="parameter">0</DiscardPacketsSent>
        <DiscardPacketsReceived node="parameter">0</DiscardPacketsReceived>
        <TotalStart node="parameter">0</TotalStart>
        <ShowtimeStart node="parameter">0</ShowtimeStart>
        <LastShowtimeStart node="parameter">0</LastShowtimeStart>
        <CurrentDayStart node="parameter">0</CurrentDayStart>
        <QuarterHourStart node="parameter">0</QuarterHourStart>
        <Total node="object">
          <XTURFECErrors node="parameter">0</XTURFECErrors>
          <XTUCFECErrors node="parameter">0</XTUCFECErrors>
          <XTURHECErrors node="parameter">0</XTURHECErrors>
          <XTUCHECErrors node="parameter">0</XTUCHECErrors>
          <XTURCRCErrors node="parameter">0</XTURCRCErrors>
          <XTUCCRCErrors node="parameter">0</XTUCCRCErrors>
        </Total>
        <Showtime node="object">
          <XTURFECErrors node="parameter">0</XTURFECErrors>
          <XTUCFECErrors node="parameter">0</XTUCFECErrors>
          <XTURHECErrors node="parameter">0</XTURHECErrors>
          <XTUCHECErrors node="parameter">0</XTUCHECErrors>
          <XTURCRCErrors node="parameter">0</XTURCRCErrors>
          <XTUCCRCErrors node="parameter">0</XTUCCRCErrors>
        </Showtime>
        <LastShowtime node="object">
          <XTURFECErrors node="parameter">0</XTURFECErrors>
          <XTUCFECErrors node="parameter">0</XTUCFECErrors>
          <XTURHECErrors node="parameter">0</XTURHECErrors>
          <XTUCHECErrors node="parameter">0</XTUCHECErrors>
          <XTURCRCErrors node="parameter">0</XTURCRCErrors>
          <XTUCCRCErrors node="parameter">0</XTUCCRCErrors>
        </LastShowtime>
        <CurrentDay node="object">
          <XTURFECErrors node="parameter">0</XTURFECErrors>
          <XTUCFECErrors node="parameter">0</XTUCFECErrors>
          <XTURHECErrors node="parameter">0</XTURHECErrors>
          <XTUCHECErrors node="parameter">0</XTUCHECErrors>
          <XTURCRCErrors node="parameter">0</XTURCRCErrors>
          <XTUCCRCErrors node="parameter">0</XTUCCRCErrors>
        </CurrentDay>
        <QuarterHour node="object">
          <XTURFECErrors node="parameter">0</XTURFECErrors>
          <XTUCFECErrors node="parameter">0</XTUCFECErrors>
          <XTURHECErrors node="parameter">0</XTURHECErrors>
          <XTUCHECErrors node="parameter">0</XTUCHECErrors>
          <XTURCRCErrors node="parameter">0</XTURCRCErrors>
          <XTUCCRCErrors node="parameter">0</XTUCCRCErrors>
        </QuarterHour>
      </Stats>
    </Channel>
    <Diagnostics node="object">
      <ADSLLineTest node="object">
        <DiagnosticsState node="parameter">None</DiagnosticsState>
        <Interface node="parameter"/>
        <ACTPSDds node="parameter">0</ACTPSDds>
        <ACTPSDus node="parameter">0</ACTPSDus>
        <ACTATPds node="parameter">0</ACTATPds>
        <ACTATPus node="parameter">0</ACTATPus>
        <HLINSCds node="parameter">0</HLINSCds>
        <HLINSCus node="parameter">0</HLINSCus>
        <HLINGds node="parameter">0</HLINGds>
        <HLINGus node="parameter">0</HLINGus>
        <HLOGGds node="parameter">0</HLOGGds>
        <HLOGGus node="parameter">0</HLOGGus>
        <HLOGpsds node="parameter"/>
        <HLOGpsus node="parameter"/>
        <HLOGMTds node="parameter">0</HLOGMTds>
        <HLOGMTus node="parameter">0</HLOGMTus>
        <LATNpbds node="parameter"/>
        <LATNpbus node="parameter"/>
        <SATNds node="parameter"/>
        <SATNus node="parameter"/>
        <HLINpsds node="parameter">0</HLINpsds>
        <HLINpsus node="parameter"/>
        <QLNGds node="parameter">0</QLNGds>
        <QLNGus node="parameter">0</QLNGus>
        <QLNpsds node="parameter">0</QLNpsds>
        <QLNpsus node="parameter">0</QLNpsus>
        <QLNMTds node="parameter">0</QLNMTds>
        <QLNMTus node="parameter">0</QLNMTus>
        <SNRGds node="parameter">0</SNRGds>
        <SNRGus node="parameter">0</SNRGus>
        <SNRpsds node="parameter">0</SNRpsds>
        <SNRpsus node="parameter">0</SNRpsus>
        <SNRMTds node="parameter">0</SNRMTds>
        <SNRMTus node="parameter">0</SNRMTus>
        <BITSpsds node="parameter">0</BITSpsds>
        <BITSpsus node="parameter">0</BITSpsus>
      </ADSLLineTest>
    </Diagnostics>
  </DSL>
</Device>
